{
  "id": "8536a1cd-a8b9-4c35-8b56-4ace1434d875",
  "title": "Provaimo",
  "owner": "Admin",
  "isActive": true,
  "questions": [
    {
      "id": 0,
      "text": "Prima domanda",
      "answers": [
        {
          "id": 0,
          "text": "Risposta 1",
          "votes": 1
        },
        {
          "id": 1,
          "text": "Risposta 2",
          "votes": 0
        }
      ]
    },
    {
      "id": 1,
      "text": "Doamnde",
      "answers": [
        {
          "id": 0,
          "text": "sad",
          "votes": 0
        },
        {
          "id": 1,
          "text": "das",
          "votes": 1
        }
      ]
    },
    {
      "id": 2,
      "text": "Troppe domande",
      "answers": [
        {
          "id": 0,
          "text": "21",
          "votes": 0
        },
        {
          "id": 1,
          "text": "3",
          "votes": 1
        }
      ]
    },
    {
      "id": 3,
      "text": "Eccoloe",
      "answers": [
        {
          "id": 0,
          "text": "321",
          "votes": 0
        },
        {
          "id": 1,
          "text": "41",
          "votes": 0
        }
      ]
    }
  ]
}